mh_django_config/__init__.py
mh_django_config/_version.py
mh_django_config/config.py
mh_django_config/parsers.py
mh_django_config/tests/__init__.py
mh_django_config/tests/test_config.py
mh_django_config/tests/test_parsers.py
mh_django_config-0.0.5.dist-info/METADATA
mh_django_config-0.0.5.dist-info/WHEEL
mh_django_config-0.0.5.dist-info/top_level.txt
mh_django_config-0.0.5.dist-info/RECORD
